{
    "card_id": 119411040,
    "foil_card_id": 119411041,
    "card_set_id": 10019,
    "card_name": "人鱼弓手",
    "card_name_ruby": "",
    "is_foil": 0,
    "char_type": 1,
    "clan": 4,
    "tribe_name": "-",
    "skill": "damage",
    "skill_condition": "character=me&target=self",
    "skill_target": "character=op&target=inplay&card_type=unit&random_count=1",
    "skill_option": "damage=2",
    "skill_preprocess": "per_turn=1",
    "skill_disc": "如果这个从者受到伤害后仍未被破坏，则会随机给予1个敌方的从者2点伤害，此效果每个回合仅限发动1次。",
    "org_skill_disc": "如果这个从者受到伤害后仍未被破坏，则会随机给予1个敌方的从者2点伤害，此效果每个回合仅限发动1次。",
    "evo_skill_disc": "与进化前能力相同。",
    "org_evo_skill_disc": "与进化前能力相同。",
    "cost": 2,
    "atk": 0,
    "life": 5,
    "evo_atk": 2,
    "evo_life": 7,
    "rarity": 1,
    "get_red_ether": 10,
    "use_red_ether": 50,
    "description": "恰如四海一家──人鱼不会嫌弃种族之别。<br>以真心回应温情，甚至能跨越种族藩篱坠入爱河。",
    "evo_description": "无论天涯海角──对盛怒的人鱼来说都不成问题。<br>一旦令她们发怒，即便逃到陆地也能报一箭之仇。",
    "cv": "内田真礼",
    "copyright": null,
    "base_card_id": 119411040,
    "normal_card_id": 119411040,
    "format_type": 0,
    "restricted_count": 3,
    "restricted_count_co_main": 3,
    "restricted_count_co_sub": 3
}