{
    "card_id": 112141030,
    "foil_card_id": 112141031,
    "card_set_id": 10012,
    "card_name": "伏贾诺沼泽之主",
    "card_name_ruby": "",
    "is_foil": 0,
    "char_type": 1,
    "clan": 1,
    "tribe_name": "-",
    "skill": "sneak,attach_skill//return_card",
    "skill_condition": "character=me,character=me&target=inplay&card_type=class//character=op&target=inplay&card_type=unit",
    "skill_target": "character=me,character=me&target=inplay&card_type=class//character=op&target=inplay&card_type=unit&select_count=1",
    "skill_option": "none,skill=(skill:damage)(timing:when_return_skill_activate)(condition:character=me&turn=self)(target:character=op&target=inplay&card_type=class)(option:damage=2*{both.return_card.count})(preprocess:none)(effect_path:btl_112141030_3)(se_path:se_btl_112141030_3)(effect_move_type:DIRECT_LEADER)(engine_type:SHURIKEN)(effect_time:0.2)(effect_target_type:single)&duplicate_ban_id=112141031//none",
    "skill_preprocess": "none,none//none",
    "skill_disc": "潜行 <br>入场曲 这场对战中，给予自己的主战者「自己的回合中，每当发动使战场上的卡片返回手牌中能力时，给予敌方的主战者与「因该能力而离开战场之卡片张数的2倍」等量的伤害」效果。主战者无法重复叠加此效果。",
    "org_skill_disc": "[u][ffcd45]潜行[-][/u] <br>[u][ffcd45]入场曲[-][/u] 这场对战中，给予自己的主战者「自己的回合中，每当发动使战场上的卡片返回手牌中能力时，给予敌方的主战者与「因该能力而离开战场之卡片张数的2倍」等量的伤害」效果。主战者无法重复叠加此效果。",
    "evo_skill_disc": "潜行 <br>进化时 使1个敌方的从者回到敌方的手牌中。",
    "org_evo_skill_disc": "[u][ffcd45]潜行[-][/u] <br>[u][ffcd45]进化时[-][/u] 使1个敌方的从者回到敌方的手牌中。",
    "cost": 8,
    "atk": 6,
    "life": 6,
    "evo_atk": 8,
    "evo_life": 8,
    "rarity": 4,
    "get_red_ether": 1000,
    "use_red_ether": 3500,
    "description": "其为森之渊。淤滞、混浊、深不见底的伏贾诺沼泽。<br>牠，存在于此，栖居于此，愤怒且狂暴的深渊之王。<br>一旦涉足渊沼，届时无论何者皆将归王所有。<br>尔后随其无常之意，或驱离境外，或遭拖入黑暗中。",
    "evo_description": "不知存在源自何时，亦不明将栖居至何日。<br>受悠久孤独所囚禁之王，持续寻找著永恒的伴侣。<br>而当得来不易的所有物，悄声逃离之时──<br>王的叹息，将撼动森林与天地。",
    "cv": "-",
    "copyright": null,
    "base_card_id": 112141030,
    "normal_card_id": 112141030,
    "format_type": 0,
    "restricted_count": 3,
    "restricted_count_co_main": 3,
    "restricted_count_co_sub": 3
}