{
    "card_id": 117711030,
    "foil_card_id": 117711031,
    "card_set_id": 10017,
    "card_name": "优雅的丽鸟",
    "card_name_ruby": "",
    "is_foil": 0,
    "char_type": 1,
    "clan": 7,
    "tribe_name": "-",
    "skill": "random_array,summon_token,summon_token",
    "skill_condition": "none,character=me,character=me",
    "skill_target": "character=me&target=self&card_type=unit,none,none",
    "skill_option": "sum=1&random_range=2,summon_token=100713020,summon_token=101713010",
    "skill_preprocess": "none,only_random_index=0,only_random_index=1",
    "skill_disc": "谢幕曲 由咏唱：召唤天马、咏唱：银翼祷告之中，随机召唤1个到战场上。",
    "org_skill_disc": "[u][ffcd45]谢幕曲[-][/u] 由[u][ffcd45]咏唱：召唤天马[-][/u]、[u][ffcd45]咏唱：银翼祷告[-][/u]之中，随机召唤1个到战场上。",
    "evo_skill_disc": "与进化前能力相同。",
    "org_evo_skill_disc": "与进化前能力相同。",
    "cost": 2,
    "atk": 3,
    "life": 1,
    "evo_atk": 5,
    "evo_life": 3,
    "rarity": 1,
    "get_red_ether": 10,
    "use_red_ether": 50,
    "description": "那羽翼从上方观赏会比较美丽的理由，有此一说：<br>为了让行经空中的伙伴能找到在纯白雪原上的牠。<br>──出自｢边境稀有鸟类图鉴｣ 白雪之彩",
    "evo_description": "那是，赠予前往天际者的羽毛。<br>落下羽毛的光辉，会使迷人的羽翼再度变化。<br>──出自｢边境稀有鸟类图鉴｣ 白雪之彩",
    "cv": "-",
    "copyright": null,
    "base_card_id": 117711030,
    "normal_card_id": 117711030,
    "format_type": 0,
    "restricted_count": 3,
    "restricted_count_co_main": 3,
    "restricted_count_co_sub": 3
}