{
    "card_id": 900841220,
    "foil_card_id": 900841221,
    "card_set_id": 90000,
    "card_name": "再诞的灾乱‧阿莱克托",
    "card_name_ruby": "",
    "is_foil": 0,
    "char_type": 1,
    "clan": 8,
    "tribe_name": "机械",
    "skill": "guard,powerup,draw",
    "skill_condition": "character=me,{me.inplay_self.count}>0,{me.inplay_self.count}>0",
    "skill_target": "character=me,character=me&target=inplay&card_type=unit&tribe=machine,character=me&target=deck&card_type=all&random_count=3",
    "skill_option": "none,add_offense=2&add_life=2,none",
    "skill_preprocess": "none,none,none",
    "skill_disc": "守护 <br>自己的回合结束时，给予自己的机械从者全体+2/+2效果。抽取3张卡片。",
    "org_skill_disc": "[u][ffcd45]守护[-][/u] <br>自己的回合结束时，给予自己的机械从者全体+2/+2效果。抽取3张卡片。",
    "evo_skill_disc": "与进化前能力相同。",
    "org_evo_skill_disc": "与进化前能力相同。",
    "cost": 9,
    "atk": 4,
    "life": 7,
    "evo_atk": 6,
    "evo_life": 9,
    "rarity": 4,
    "get_red_ether": 0,
    "use_red_ether": 0,
    "description": "冠名灾乱，职责为破坏。<br>再诞的女神毫无赦免，以禁忌的罪罚蹂躏践踏。<br>那正是，其身被赋生的意义。",
    "evo_description": "使用素材A。双子型同步协力机──第二型銡。<br>欲传达自我的共感心，因失望而患病、消除记忆体。<br>使用素材B。双子型同步协力机──第三型朵莉。<br>欲知悉他人的好奇心，因倦怠而忧愁、消除记忆体。",
    "cv": "小清水亚美",
    "copyright": null,
    "base_card_id": 900841220,
    "normal_card_id": 900841220,
    "format_type": 0,
    "restricted_count": 3,
    "restricted_count_co_main": 3,
    "restricted_count_co_sub": 3
}