{
    "card_id": 101211070,
    "foil_card_id": 101211071,
    "card_set_id": 10001,
    "card_name": "勇猛的骑士",
    "card_name_ruby": "",
    "is_foil": 0,
    "char_type": 1,
    "clan": 2,
    "tribe_name": "士兵",
    "skill": "summon_token",
    "skill_condition": "character=me",
    "skill_target": "none",
    "skill_option": "summon_token=900211030",
    "skill_preprocess": "none",
    "skill_disc": "入场曲 召唤1个铁甲骑士到战场上。",
    "org_skill_disc": "[u][ffcd45]入场曲[-][/u] 召唤1个[u][ffcd45]铁甲骑士[-][/u]到战场上。",
    "evo_skill_disc": "",
    "org_evo_skill_disc": "",
    "cost": 4,
    "atk": 2,
    "life": 2,
    "evo_atk": 4,
    "evo_life": 4,
    "rarity": 1,
    "get_red_ether": 10,
    "use_red_ether": 50,
    "description": "能为王的一个命令献上生命，这就是我们的职责！在战场上绽放最后光芒，才是骑士们所追求的荣誉。",
    "evo_description": "就算剑被毁，铠甲被破坏，但是我等的信念却不会熄灭！你们这些败类恶徒，觉悟吧！",
    "cv": "川田绅司",
    "copyright": null,
    "base_card_id": 101211070,
    "normal_card_id": 101211070,
    "format_type": 0,
    "restricted_count": 3,
    "restricted_count_co_main": 3,
    "restricted_count_co_sub": 3
}