{
    "card_id": 116834010,
    "foil_card_id": 116834011,
    "card_set_id": 10016,
    "card_name": "反叛命运",
    "card_name_ruby": "",
    "is_foil": 0,
    "char_type": 4,
    "clan": 8,
    "tribe_name": "-",
    "skill": "pp_modifier,choice,transform,summon_token,token_draw",
    "skill_condition": "resonance=false,resonance=false,character=me&target=chosen_cards&card_type=all&resonance=false,resonance=true,resonance=true",
    "skill_target": "character=me&target=inplay&card_type=class,none,target=chosen_cards&card_type=all,none,none",
    "skill_option": "gain_pp={me.self.cost}&is_before_choice_transform=true,card_id=900834050:900834060,repeat_count=1&summon_side=me,summon_token=900811020:900811010,token_draw=900841110:900841120:900841130:?1",
    "skill_preprocess": "none,none,none,none,none",
    "skill_disc": "‧伊昂的愤怒<br>‧贝尔弗特的镇压<br>使自己的PP消耗与这张卡片等量的消费值，在使用这张卡片时将其转变为命运抉择 所指定的卡片。<br>如果共鸣 状态已发动，则会由原本的命运抉择 转变为召唤1个神秘的创造物与1个古老的创造物到战场上。由杀戮女神‧提西福涅、灾乱女神‧阿莱克托、愤怒女神‧墨盖拉之中，随机增加1张卡片到手牌中。",
    "org_skill_disc": "‧[u][ffcd45]伊昂的愤怒[-][/u]<br>‧[u][ffcd45]贝尔弗特的镇压[-][/u]<br>使自己的PP消耗与这张卡片等量的消费值，在使用这张卡片时将其转变为[u][ffcd45]命运抉择[-][/u] 所指定的卡片。<br>如果[u][ffcd45]共鸣[-][/u] 状态已发动，则会由原本的[u][ffcd45]命运抉择[-][/u] 转变为召唤1个[u][ffcd45]神秘的创造物[-][/u]与1个[u][ffcd45]古老的创造物[-][/u]到战场上。由[u][ffcd45]杀戮女神‧提西福涅[-][/u]、[u][ffcd45]灾乱女神‧阿莱克托[-][/u]、[u][ffcd45]愤怒女神‧墨盖拉[-][/u]之中，随机增加1张卡片到手牌中。",
    "evo_skill_disc": "",
    "org_evo_skill_disc": "",
    "cost": 4,
    "atk": 0,
    "life": 0,
    "evo_atk": 0,
    "evo_life": 0,
    "rarity": 3,
    "get_red_ether": 250,
    "use_red_ether": 800,
    "description": "与决意齐心，超越命运吧。<br>那话语正是，叛乱的开端。<br>「抗战的时刻已到。走吧，一同开创未来吧！」",
    "evo_description": "",
    "cv": "柿原彻也",
    "copyright": null,
    "base_card_id": 116834010,
    "normal_card_id": 116834010,
    "format_type": 0,
    "restricted_count": 3,
    "restricted_count_co_main": 3,
    "restricted_count_co_sub": 3
}