{
    "card_id": 124631010,
    "foil_card_id": 124631011,
    "card_set_id": 10024,
    "card_name": "变幻自如的伪装者",
    "card_name_ruby": "",
    "is_foil": 0,
    "char_type": 1,
    "clan": 6,
    "tribe_name": "-",
    "skill": "force_berserk,powerup",
    "skill_condition": "character=me,{me.inplay_self.count}>0&character=me&target=summoned_card&card_type=unit&turn=self&clan=vampire&berserk=true",
    "skill_target": "character=me&target=inplay&card_type=class,{me.self}&{me.summoned_card.unit.clan=vampire.is_inplay=true}",
    "skill_option": "none,add_offense=1&add_life=1",
    "skill_preprocess": "turn_end_period_of_stop_time=1:0,none",
    "skill_disc": "如果这张卡片因能力被从手牌中舍弃，则到下个自己的回合结束为止，即使自己主战者的生命值为11以上，也会发动复仇 状态。<br>---------- <br>自己的回合中，当其他吸血鬼从者进入自己的战场时，如果复仇 状态已发动，则会给予该从者与这个从者+1/+1效果。",
    "org_skill_disc": "如果这张卡片因能力被从手牌中舍弃，则到下个自己的回合结束为止，即使自己主战者的生命值为11以上，也会发动[u][ffcd45]复仇[-][/u] 状态。<br>---------- <br>自己的回合中，当其他吸血鬼从者进入自己的战场时，如果[u][ffcd45]复仇[-][/u] 状态已发动，则会给予该从者与这个从者+1/+1效果。",
    "evo_skill_disc": "与进化前能力相同。",
    "org_evo_skill_disc": "与进化前能力相同。",
    "cost": 3,
    "atk": 3,
    "life": 3,
    "evo_atk": 5,
    "evo_life": 5,
    "rarity": 3,
    "get_red_ether": 250,
    "use_red_ether": 800,
    "description": "哇……惨了。你看到了？被你发现了？被你知道了？<br>失策啊──还想说很喜欢用这张脸生活的说。<br>唉，算了。久违地回到怪物身姿吧。",
    "evo_description": "我对人类、对他人都很有兴趣，<br>因此一直变化身形观察著你们。<br>不管看多久都无法理解，但看不够也看不腻。<br>呐，为什么你们能这么弱小地活著呢？",
    "cv": "浦和希",
    "copyright": null,
    "base_card_id": 124631010,
    "normal_card_id": 124631010,
    "format_type": 1,
    "restricted_count": 3,
    "restricted_count_co_main": 3,
    "restricted_count_co_sub": 3
}