{
    "card_id": 101021040,
    "foil_card_id": 101021041,
    "card_set_id": 10001,
    "card_name": "哥布林巨魔骑士",
    "card_name_ruby": "",
    "is_foil": 0,
    "char_type": 1,
    "clan": 0,
    "tribe_name": "-",
    "skill": "guard,damage",
    "skill_condition": "character=me,character=me&target=inplay_other_self&card_type=unit",
    "skill_target": "character=me,character=me&target=inplay_other_self&card_type=unit",
    "skill_option": "none,damage=3",
    "skill_preprocess": "none,none",
    "skill_disc": "守护 <br>入场曲 给予自己的其他从者全体3点伤害。",
    "org_skill_disc": "[u][ffcd45]守护[-][/u] <br>[u][ffcd45]入场曲[-][/u] 给予自己的其他从者全体3点伤害。",
    "evo_skill_disc": "与进化前能力相同。（入场曲 能力除外）",
    "org_evo_skill_disc": "与进化前能力相同。（[u][ffcd45]入场曲[-][/u] 能力除外）",
    "cost": 5,
    "atk": 3,
    "life": 7,
    "evo_atk": 5,
    "evo_life": 9,
    "rarity": 2,
    "get_red_ether": 50,
    "use_red_ether": 200,
    "description": "「快给我工作！你只是个光长肌肉没长脑的蠢材，所以要乖乖听我的话啊！」「吼！」「动作快！太阳下山之后就危险了！再慢吞吞的话你就准备吃鞭子吧！」「吼吼！」",
    "evo_description": "「惨了啦！被包围了啦！怎么办啦！」「吼呜喔喔喔喔！」「你小子……真是救了我一命！谢啦！」「谁叫我迷上你了呢。」「你竟然是喜欢这味的！？……不对，你原来会说话！？」",
    "cv": "滨野大辉",
    "copyright": null,
    "base_card_id": 101021040,
    "normal_card_id": 101021040,
    "format_type": 0,
    "restricted_count": 3,
    "restricted_count_co_main": 3,
    "restricted_count_co_sub": 3
}