{
    "card_id": 102731030,
    "foil_card_id": 102731031,
    "card_set_id": 10002,
    "card_name": "天空守护者‧迦楼罗",
    "card_name_ruby": "",
    "is_foil": 0,
    "char_type": 1,
    "clan": 7,
    "tribe_name": "-",
    "skill": "chant_count_change,damage",
    "skill_condition": "character=me&target=inplay&card_type=chant_field,character=op&target=inplay&card_type=class",
    "skill_target": "character=me&target=inplay&card_type=chant_field&select_count=1,character=op&target=inplay&card_type=class",
    "skill_option": "gain_chant=3,damage=3",
    "skill_preprocess": "none,none",
    "skill_disc": "入场曲 使1个自己的护符减少3回合倒数 ，并给予敌方的主战者3点伤害。",
    "org_skill_disc": "[u][ffcd45]入场曲[-][/u] 使1个自己的护符减少3回合[u][ffcd45]倒数[-][/u] ，并给予敌方的主战者3点伤害。",
    "evo_skill_disc": "",
    "org_evo_skill_disc": "",
    "cost": 6,
    "atk": 4,
    "life": 4,
    "evo_atk": 6,
    "evo_life": 6,
    "rarity": 3,
    "get_red_ether": 250,
    "use_red_ether": 800,
    "description": "统领鹰之一族的领袖，同时也是接受了天之祝福的黄金翼神。引导比谁都要追求天空最高处的翼之魂前往天界。",
    "evo_description": "操控天候以维持世界均衡的翼神。锐利的双眼所盼望的未来，是能以秩序守护全天空有翼者的梦想乐园。",
    "cv": "速水奖",
    "copyright": null,
    "base_card_id": 102731030,
    "normal_card_id": 102731030,
    "format_type": 0,
    "restricted_count": 3,
    "restricted_count_co_main": 3,
    "restricted_count_co_sub": 3
}