{
    "card_id": 127231010,
    "foil_card_id": 127231011,
    "card_set_id": 10027,
    "card_name": "怒涛副船长",
    "card_name_ruby": "",
    "is_foil": 0,
    "char_type": 1,
    "clan": 2,
    "tribe_name": "士兵‧八狱",
    "skill": "summon_token,token_draw,token_draw//summon_token,cost_change",
    "skill_condition": "{me.inplay_self.count}>0&character=me&target=played_card&card_type=all&tribe=looting,{me.game_play_cards_other_self.all.play_moment_tribe=looting.count}+{me.game_fusion_ingrediented_cards.all.tribe=looting.count}<7,{me.game_play_cards_other_self.all.play_moment_tribe=looting.count}+{me.game_fusion_ingrediented_cards.all.tribe=looting.count}>=7//{me.inplay_self.count}>0&character=me&target=played_card&card_type=all&tribe=looting,character=me",
    "skill_target": "none,none,none//none,character=me&target=hand_other_self&card_type=all&tribe=looting&select_count=1",
    "skill_option": "summon_token=900211100,token_draw=900214040,token_draw=900214060//summon_token=900211090,add=-1",
    "skill_preprocess": "none,none,none//none,none",
    "skill_disc": "当自己使用财宝卡时，召唤1个巡洋突击兵到战场上。<br>入场曲 增加1张黄金首饰卡片到手牌中。如果自己在这场对战中融合 或已使用的财宝卡张数合计为7张以上，则会由原本的黄金首饰转变为增加战栗的海贼旗卡片到手牌中。",
    "org_skill_disc": "当自己使用财宝卡时，召唤1个[u][ffcd45]巡洋突击兵[-][/u]到战场上。<br>[u][ffcd45]入场曲[-][/u] 增加1张[u][ffcd45]黄金首饰[-][/u]卡片到手牌中。如果自己在这场对战中[u][ffcd45]融合[-][/u] 或已使用的财宝卡张数合计为7张以上，则会由原本的[u][ffcd45]黄金首饰[-][/u]转变为增加[u][ffcd45]战栗的海贼旗[-][/u]卡片到手牌中。",
    "evo_skill_disc": "当自己使用财宝卡时，召唤1个加农炮水手到战场上。<br>进化时 使1张自己手牌中的财宝卡消费-1。",
    "org_evo_skill_disc": "当自己使用财宝卡时，召唤1个[u][ffcd45]加农炮水手[-][/u]到战场上。<br>[u][ffcd45]进化时[-][/u] 使1张自己手牌中的财宝卡消费-1。",
    "cost": 3,
    "atk": 2,
    "life": 2,
    "evo_atk": 4,
    "evo_life": 4,
    "rarity": 3,
    "get_red_ether": 250,
    "use_red_ether": 800,
    "description": "老爸的教诲实在太仁慈。既不杀恶也不夺善。<br>没效率到让我都快吐了，就像这艘船一样过时。<br>真让人浑身不舒服呢。唉，总觉得很……不自由。<br>──第七阶层特级囚人的提取记忆 5",
    "evo_description": "杀敌就会削减战力。抢夺平民损害就会降到最低。<br>结果与成果已证明，这就是自由。老爸才是掠夺者。<br>他用名为教诲的诅咒将我束缚，夺取了我的自由。<br>──第七阶层特级囚人的提取记忆 6",
    "cv": "关智一",
    "copyright": null,
    "base_card_id": 127231010,
    "normal_card_id": 127231010,
    "format_type": 1,
    "restricted_count": 3,
    "restricted_count_co_main": 3,
    "restricted_count_co_sub": 3
}