{
    "card_id": 124411010,
    "foil_card_id": 124411011,
    "card_set_id": 10024,
    "card_name": "接送的走龙",
    "card_name_ruby": "",
    "is_foil": 0,
    "char_type": 1,
    "clan": 4,
    "tribe_name": "宴乐",
    "skill": "summon_token,summon_token",
    "skill_condition": "character=me&target=inplay_self,character=me",
    "skill_target": "none,none",
    "skill_option": "summon_token=900411030,summon_token=900411030",
    "skill_preprocess": "none,none",
    "skill_disc": "当这个从者的攻击力或生命值因能力而获得+效果时，召唤1只虎鲸到战场上。<br>入场曲 召唤1只虎鲸到战场上。",
    "org_skill_disc": "当这个从者的攻击力或生命值因能力而获得+效果时，召唤1只[u][ffcd45]虎鲸[-][/u]到战场上。<br>[u][ffcd45]入场曲[-][/u] 召唤1只[u][ffcd45]虎鲸[-][/u]到战场上。",
    "evo_skill_disc": "与进化前能力相同。（入场曲 能力除外）",
    "org_evo_skill_disc": "与进化前能力相同。（[u][ffcd45]入场曲[-][/u] 能力除外）",
    "cost": 3,
    "atk": 1,
    "life": 2,
    "evo_atk": 3,
    "evo_life": 4,
    "rarity": 1,
    "get_red_ether": 10,
    "use_red_ether": 50,
    "description": "你第一次搭龙车吗？虽然有点窄，但忍耐一下吧。<br>要去山上的话，就得靠这家伙的鼻子。<br>问我为什么？当然是因为不知道温泉会跑去哪里啊。<br>──龙背之汤 1",
    "evo_description": "这只龙也因为泡了温泉才能继续奔驰。<br>当然我也是啦。对了……小哥！<br>如果那只手治好的话，要不要一起去赏花啊？<br>──龙背之汤 2",
    "cv": "-",
    "copyright": null,
    "base_card_id": 124411010,
    "normal_card_id": 124411010,
    "format_type": 1,
    "restricted_count": 3,
    "restricted_count_co_main": 3,
    "restricted_count_co_sub": 3
}