{
    "card_id": 127821030,
    "foil_card_id": 127821031,
    "card_set_id": 10027,
    "card_name": "改造技师",
    "card_name_ruby": "",
    "is_foil": 0,
    "char_type": 1,
    "clan": 8,
    "tribe_name": "-",
    "skill": "summon_token//evolve",
    "skill_condition": "character=me//character=me",
    "skill_target": "none//character=me&target=inplay_other_self&card_type=unit&evolution=false&base_card_id=106331020&random_count=1",
    "skill_option": "summon_token=106331020//none",
    "skill_preprocess": "none//none",
    "skill_disc": "入场曲 召唤1个暴虐的巨像到战场上。",
    "org_skill_disc": "[u][ffcd45]入场曲[-][/u] 召唤1个[u][ffcd45]暴虐的巨像[-][/u]到战场上。",
    "evo_skill_disc": "进化时 随机使1个自己「未进化的暴虐的巨像」进化。",
    "org_evo_skill_disc": "[u][ffcd45]进化时[-][/u] 随机使1个自己「未进化的[u][ffcd45]暴虐的巨像[-][/u]」进化。",
    "cost": 4,
    "atk": 2,
    "life": 2,
    "evo_atk": 4,
    "evo_life": 4,
    "rarity": 2,
    "get_red_ether": 50,
    "use_red_ether": 200,
    "description": "战斗？实在野蛮，头脑真笨。<br>对那种废物还需要攻击机能吗？<br>外装强化也只要防水就够了。<br>这样就能华丽地拯救城镇。",
    "evo_description": "这些家伙？是虫喔。<br>习性都一样。只要被光吸引就会一拥而上。<br>意思是真正的技师，技术和头脑都是很厉害的啦。<br>好了，快要到河川了喔！",
    "cv": "浅仓杏美",
    "copyright": null,
    "base_card_id": 127821030,
    "normal_card_id": 127821030,
    "format_type": 1,
    "restricted_count": 3,
    "restricted_count_co_main": 3,
    "restricted_count_co_sub": 3
}