{
    "card_id": 113041010,
    "foil_card_id": 113041011,
    "card_set_id": 10013,
    "card_name": "暗之翼‧奥莉薇",
    "card_name_ruby": "",
    "is_foil": 0,
    "char_type": 1,
    "clan": 0,
    "tribe_name": "-",
    "skill": "consume_ep_modifier,pp_modifier",
    "skill_condition": "character=me&target=played_card&card_type=unit&{me.inplay_self.count}>0,character=me",
    "skill_target": "character=me&target=played_card&card_type=unit,character=me&target=inplay&card_type=class",
    "skill_option": "none,add_pp={me.evolved_card_list.count}",
    "skill_preprocess": "per_turn=1,none",
    "skill_disc": "当自己使用其他从者卡时，给予该从者「不消费EP即可进化」效果。（每个自己的回合仅限发动1次）（1回合中依旧只能进化1张卡片）<br>入场曲 回复自己的PP X点。X为「这场对战中，自己的从者进化的次数」。",
    "org_skill_disc": "当自己使用其他从者卡时，给予该从者「不消费EP即可进化」效果。（每个自己的回合仅限发动1次）（1回合中依旧只能进化1张卡片）<br>[u][ffcd45]入场曲[-][/u] 回复自己的PP X点。X为「这场对战中，自己的从者进化的次数」。",
    "evo_skill_disc": "与进化前能力相同。（入场曲 能力除外）",
    "org_evo_skill_disc": "与进化前能力相同。（[u][ffcd45]入场曲[-][/u] 能力除外）",
    "cost": 8,
    "atk": 5,
    "life": 5,
    "evo_atk": 7,
    "evo_life": 7,
    "rarity": 4,
    "get_red_ether": 1000,
    "use_red_ether": 3500,
    "description": "众神制定之理，即为被囚禁的希望。<br>我已经不再犹豫……只有笔直前进一途。<br>天上众神啊，想将此理想唤作愚行，就随你们的意吧。<br>即使这样我也不会停止前进，直到最后的瞬间！",
    "evo_description": "在紧闭的门后方，希望正等待著。<br>在到达新世界之前，我的羽翼将不会停止。<br>所有阻碍者都做好觉悟吧……<br>我会用魔剑之刃斩断一切！",
    "cv": "坂本真绫",
    "copyright": null,
    "base_card_id": 113041010,
    "normal_card_id": 113041010,
    "format_type": 0,
    "restricted_count": 3,
    "restricted_count_co_main": 3,
    "restricted_count_co_sub": 3
}