{
    "card_id": 102321020,
    "foil_card_id": 102321021,
    "card_set_id": 10002,
    "card_name": "暗影女巫",
    "card_name_ruby": "",
    "is_foil": 0,
    "char_type": 1,
    "clan": 3,
    "tribe_name": "-",
    "skill": "metamorphose",
    "skill_condition": "character=op&target=inplay&card_type=unit_and_allfield&{op.inplay.unit_and_allfield.selectable.count}>0",
    "skill_target": "character=op&target=inplay&card_type=unit_and_allfield&select_count=1",
    "skill_option": "metamorphose=900311020",
    "skill_preprocess": "destroy_tribe=white_ritual",
    "skill_disc": "入场曲 如果敌方的战场上有可指定的卡片，则会发动土之秘术 使1个敌方的从者或1个敌方的护符变身为泥尘巨像。",
    "org_skill_disc": "[u][ffcd45]入场曲[-][/u] 如果敌方的战场上有可指定的卡片，则会发动[u][ffcd45]土之秘术[-][/u] 使1个敌方的从者或1个敌方的护符变身为[u][ffcd45]泥尘巨像[-][/u]。",
    "evo_skill_disc": "",
    "org_evo_skill_disc": "",
    "cost": 6,
    "atk": 5,
    "life": 5,
    "evo_atk": 7,
    "evo_life": 7,
    "rarity": 2,
    "get_red_ether": 50,
    "use_red_ether": 200,
    "description": "你的长相可真荒谬呢……我来给你个新造型吧！",
    "evo_description": "看来看去还是觉得你长得有够悲剧呢……能不能快从这世界上给我消失呢？",
    "cv": "植田佳奈",
    "copyright": null,
    "base_card_id": 102321020,
    "normal_card_id": 102321020,
    "format_type": 0,
    "restricted_count": 3,
    "restricted_count_co_main": 3,
    "restricted_count_co_sub": 3
}