{
    "card_id": 110441030,
    "foil_card_id": 110441031,
    "card_set_id": 10010,
    "card_name": "暴龙‧伊达政宗",
    "card_name_ruby": "",
    "is_foil": 0,
    "char_type": 1,
    "clan": 4,
    "tribe_name": "-",
    "skill": "killer,rush,shield",
    "skill_condition": "character=me,{me.inplay.class.max_pp}=10,{me.inplay.class.max_pp}=10",
    "skill_target": "character=me&target=self,character=me&target=inplay&card_type=unit&clan=dragon,character=me&target=inplay&card_type=unit&clan=dragon",
    "skill_option": "none,none,none",
    "skill_preprocess": "none,none,turn_end_stop=me",
    "skill_disc": "必杀 <br>入场曲 如果自己的PP最大值为10，则会给予自己的龙族从者全体突进 与到回合结束为止「受到的伤害皆转变为0」效果。",
    "org_skill_disc": "[u][ffcd45]必杀[-][/u] <br>[u][ffcd45]入场曲[-][/u] 如果自己的PP最大值为10，则会给予自己的龙族从者全体[u][ffcd45]突进[-][/u] 与到回合结束为止「受到的伤害皆转变为0」效果。",
    "evo_skill_disc": "与进化前能力相同。（入场曲 能力除外）",
    "org_evo_skill_disc": "与进化前能力相同。（[u][ffcd45]入场曲[-][/u] 能力除外）",
    "cost": 2,
    "atk": 2,
    "life": 2,
    "evo_atk": 4,
    "evo_life": 4,
    "rarity": 4,
    "get_red_ether": 1000,
    "use_red_ether": 3500,
    "description": "你们这些家伙伤害了我的人民，<br>这已经触犯到我的逆鳞了。<br>胆敢吵醒沉睡中的龙……这愚行的代价可是很高的！<br>来吧！慑服于我的咆哮吧！",
    "evo_description": "心受怒火灼烧，似连失去的那只眼也欲睁目怒视！<br>这正是沉睡于我心中的龙之暴威！<br>唤醒它的可是你们这些家伙……<br>在我冷静下来之前，可别给我先死了啊！",
    "cv": "杉田智和",
    "copyright": null,
    "base_card_id": 110441030,
    "normal_card_id": 110441030,
    "format_type": 0,
    "restricted_count": 3,
    "restricted_count_co_main": 3,
    "restricted_count_co_sub": 3
}