{
    "card_id": 121241020,
    "foil_card_id": 121241021,
    "card_set_id": 10021,
    "card_name": "月光执行者‧里欧德",
    "card_name_ruby": "",
    "is_foil": 0,
    "char_type": 1,
    "clan": 2,
    "tribe_name": "指挥官",
    "skill": "sneak,damage,evolve//damage",
    "skill_condition": "character=me,{me.inplay_self.count}>0,{me.destroyed_card_list.unit.count}>=10//{me.inplay_self.count}>0",
    "skill_target": "character=me,character=op&target=inplay&card_type=unit_and_class,character=me//character=op&target=inplay&card_type=unit_and_class",
    "skill_option": "none,damage=1,none//damage=3",
    "skill_preprocess": "none,evolution_end_stop,none//none",
    "skill_disc": "潜行 <br>自己的回合开始时，给予敌方的主战者与敌方的从者全体1点伤害。<br>入场曲 如果本次对战中自己已被破坏的从者数为10个以上，则会使这个从者进化。",
    "org_skill_disc": "[u][ffcd45]潜行[-][/u] <br>自己的回合开始时，给予敌方的主战者与敌方的从者全体1点伤害。<br>[u][ffcd45]入场曲[-][/u] 如果本次对战中自己已被破坏的从者数为10个以上，则会使这个从者进化。",
    "evo_skill_disc": "潜行 <br>自己的回合开始时，给予敌方的主战者与敌方的从者全体3点伤害。",
    "org_evo_skill_disc": "[u][ffcd45]潜行[-][/u] <br>自己的回合开始时，给予敌方的主战者与敌方的从者全体3点伤害。",
    "cost": 3,
    "atk": 1,
    "life": 4,
    "evo_atk": 3,
    "evo_life": 6,
    "rarity": 4,
    "get_red_ether": 1000,
    "use_red_ether": 3500,
    "description": "一切皆是为了运河的辉耀。<br>我们是夜月……是将伊兹尼亚的黑暗铲除的利刃。<br>若能照亮这个国家的未来，我们乐于潜伏在黑暗。<br>水滴的混浊由夜月矫正，将后悔与生命一并放下吧。",
    "evo_description": "被历史射落的真相，与太阳同在的正义夜月，<br>即为在暗地援助伊兹尼亚的暗杀部队。<br>过去存于恒暗的男子赌上身命，将荣耀寄托的地方。<br>纵然被历史埋葬，其功绩已铭刻在水滴的闪耀中。",
    "cv": "石冢运升",
    "copyright": null,
    "base_card_id": 121241020,
    "normal_card_id": 121241020,
    "format_type": 0,
    "restricted_count": 3,
    "restricted_count_co_main": 3,
    "restricted_count_co_sub": 3
}