{
    "card_id": 900844010,
    "foil_card_id": 900844011,
    "card_set_id": 90000,
    "card_name": "格莱亚斯的威光",
    "card_name_ruby": "",
    "is_foil": 0,
    "char_type": 4,
    "clan": 8,
    "tribe_name": "机械",
    "skill": "powerup",
    "skill_condition": "character=me&target=inplay&card_type=unit&tribe=machine",
    "skill_target": "character=me&target=inplay&card_type=unit&tribe=machine",
    "skill_option": "add_offense=2&add_life=2",
    "skill_preprocess": "none",
    "skill_disc": "给予自己的机械从者全体+2/+2效果。",
    "org_skill_disc": "给予自己的机械从者全体+2/+2效果。",
    "evo_skill_disc": "",
    "org_evo_skill_disc": "",
    "cost": 3,
    "atk": 0,
    "life": 0,
    "evo_atk": 0,
    "evo_life": 0,
    "rarity": 4,
    "get_red_ether": 0,
    "use_red_ether": 0,
    "description": "百机之王的光辉，令无心者也振奋高昂。",
    "evo_description": "",
    "cv": "-",
    "copyright": null,
    "base_card_id": 900844010,
    "normal_card_id": 900844010,
    "format_type": 0,
    "restricted_count": 3,
    "restricted_count_co_main": 3,
    "restricted_count_co_sub": 3
}