{
    "card_id": 112111020,
    "foil_card_id": 112111021,
    "card_set_id": 10012,
    "card_name": "森之隐者",
    "card_name_ruby": "",
    "is_foil": 0,
    "char_type": 1,
    "clan": 1,
    "tribe_name": "-",
    "skill": "draw",
    "skill_condition": "character=me",
    "skill_target": "character=me&target=deck&card_type=all&tribe=machine&random_count=1",
    "skill_option": "none",
    "skill_preprocess": "none",
    "skill_disc": "入场曲 随机将1张机械卡，由自己的牌堆抽取到手牌中。",
    "org_skill_disc": "[u][ffcd45]入场曲[-][/u] 随机将1张机械卡，由自己的牌堆抽取到手牌中。",
    "evo_skill_disc": "",
    "org_evo_skill_disc": "",
    "cost": 3,
    "atk": 2,
    "life": 2,
    "evo_atk": 4,
    "evo_life": 4,
    "rarity": 1,
    "get_red_ether": 10,
    "use_red_ether": 50,
    "description": "居然将不需要的机械丢弃在森林里……<br>还真会替其他人添麻烦呀。<br>身为森林的居民，这些就由我保管吧……<br>不需要客气，住在森林里本来就该互相帮助的。",
    "evo_description": "来把捡来的零件，找个地方装饰起来吧！<br>不，或许也可以把昨天捡到的零件结合在一起……<br>呵呵……一把年纪了，还是会为梦想与浪漫雀跃啊。<br>我会偷偷研究机械，这种事谁都不会料到。",
    "cv": "伊东健人",
    "copyright": null,
    "base_card_id": 112111020,
    "normal_card_id": 112111020,
    "format_type": 0,
    "restricted_count": 3,
    "restricted_count_co_main": 3,
    "restricted_count_co_sub": 3
}