{
    "card_id": 119411010,
    "foil_card_id": 119411011,
    "card_set_id": 10019,
    "card_name": "残影龙人",
    "card_name_ruby": "",
    "is_foil": 0,
    "char_type": 1,
    "clan": 4,
    "tribe_name": "-",
    "skill": "quick,attach_skill",
    "skill_condition": "character=me,character=me&awake=true",
    "skill_target": "character=me,character=me&target=self",
    "skill_option": "none,skill=(skill:summon_token)(timing:when_destroy)(condition:character=me)(target:none)(option:summon_token=119411010)(preprocess:none)",
    "skill_preprocess": "none,none",
    "skill_disc": "疾驰 <br>入场曲 如果觉醒 状态已发动，则会获得「谢幕曲 召唤1个残影龙人到战场上」效果。",
    "org_skill_disc": "[u][ffcd45]疾驰[-][/u] <br>[u][ffcd45]入场曲[-][/u] 如果[u][ffcd45]觉醒[-][/u] 状态已发动，则会获得「[u][ffcd45]谢幕曲[-][/u] 召唤1个[u][ffcd45]残影龙人[-][/u]到战场上」效果。",
    "evo_skill_disc": "与进化前能力相同。（入场曲 能力除外）",
    "org_evo_skill_disc": "与进化前能力相同。（[u][ffcd45]入场曲[-][/u] 能力除外）",
    "cost": 4,
    "atk": 3,
    "life": 2,
    "evo_atk": 5,
    "evo_life": 4,
    "rarity": 1,
    "get_red_ether": 10,
    "use_red_ether": 50,
    "description": "斩击一闪──在少女的瞬速前，敌人屈膝跪下。<br>「音速双牙。奥义──咻咻斩击！」",
    "evo_description": "斩击一闪──理应捕捉到少女的敌刃挥空了。<br>「你刚才砍中的是残影。隐藏奥义──咻咻飞跃！」",
    "cv": "ゆかな",
    "copyright": null,
    "base_card_id": 119411010,
    "normal_card_id": 119411010,
    "format_type": 0,
    "restricted_count": 3,
    "restricted_count_co_main": 3,
    "restricted_count_co_sub": 3
}