{
    "card_id": 107641010,
    "foil_card_id": 107641011,
    "card_set_id": 10007,
    "card_name": "沃普尔吉斯",
    "card_name_ruby": "",
    "is_foil": 0,
    "char_type": 1,
    "clan": 6,
    "tribe_name": "-",
    "skill": "attach_skill,attach_skill",
    "skill_condition": "character=me,character=me",
    "skill_target": "character=me&target=inplay&card_type=class,character=op&target=inplay&card_type=class",
    "skill_option": "skill=(skill:damage)(timing:self_turn_end)(condition:character=me&target=inplay&card_type=class)(target:character=me&target=inplay&card_type=class)(option:damage=1)(preprocess:none)(effect_path:btl_unique_nacht_3)(se_path:se_btl_unique_nacht_3)(effect_move_type:DIRECT)(engine_type:SHURIKEN)(effect_time:0.2)(effect_target_type:single),skill=(skill:damage)(timing:self_turn_end)(condition:character=me&target=inplay&card_type=class)(target:character=me&target=inplay&card_type=class)(option:damage=1)(preprocess:none)(effect_path:btl_unique_nacht_3)(se_path:se_btl_unique_nacht_3)(effect_move_type:DIRECT)(engine_type:SHURIKEN)(effect_time:0.2)(effect_target_type:single)",
    "skill_preprocess": "none,none",
    "skill_disc": "谢幕曲 这场对战中，给予双方的主战者「自己的回合结束时，给予自己的主战者1点伤害」效果。",
    "org_skill_disc": "[u][ffcd45]谢幕曲[-][/u] 这场对战中，给予双方的主战者「自己的回合结束时，给予自己的主战者1点伤害」效果。",
    "evo_skill_disc": "与进化前能力相同。",
    "org_evo_skill_disc": "与进化前能力相同。",
    "cost": 5,
    "atk": 4,
    "life": 4,
    "evo_atk": 6,
    "evo_life": 6,
    "rarity": 4,
    "get_red_ether": 1000,
    "use_red_ether": 3500,
    "description": "称我们为妖魔鬼怪，扬言要狩猎我们是吧。<br>甚至还狂妄地说要给予我们正义的制裁对吧。<br>那我就化为妖魔鬼怪，来狩猎你们吧。<br>人类的世界已经结束了，开始魔女的狂欢之夜吧。",
    "evo_description": "人类将我们沉入了水底，<br>那我们就将这个世界浸入黑暗之中吧。<br>憎恨、厌恶，啊，我恨透了你们的一切。<br>寂静的夜晚已不会再到来，血染之夜将拉开序幕。",
    "cv": "小清水亚美",
    "copyright": null,
    "base_card_id": 107641010,
    "normal_card_id": 107641010,
    "format_type": 0,
    "restricted_count": 3,
    "restricted_count_co_main": 3,
    "restricted_count_co_sub": 3
}