{
    "card_id": 117641020,
    "foil_card_id": 117641021,
    "card_set_id": 10017,
    "card_name": "深渊之契‧达尔霍德",
    "card_name_ruby": "",
    "is_foil": 0,
    "char_type": 1,
    "clan": 6,
    "tribe_name": "-",
    "skill": "destroy,damage//damage,summon_token",
    "skill_condition": "{op.inplay.unit.selectable.count}>0&wrath=true,character=me&wrath=true//character=me,character=me",
    "skill_target": "character=op&target=inplay&card_type=unit&select_count=1,character=op&target=inplay&card_type=class//character=me&target=inplay&card_type=class,none",
    "skill_option": "none,damage=3//damage=3,summon_token=101633010",
    "skill_preprocess": "none,none//none,none",
    "skill_disc": "入场曲 如果狂乱 状态已发动，则会破坏1个敌方的从者。给予敌方的主战者3点伤害。",
    "org_skill_disc": "[u][ffcd45]入场曲[-][/u] 如果[u][ffcd45]狂乱[-][/u] 状态已发动，则会破坏1个敌方的从者。给予敌方的主战者3点伤害。",
    "evo_skill_disc": "进化时 给予自己的主战者3点伤害。召唤1个漆黑之契到战场上。",
    "org_evo_skill_disc": "[u][ffcd45]进化时[-][/u] 给予自己的主战者3点伤害。召唤1个[u][ffcd45]漆黑之契[-][/u]到战场上。",
    "cost": 4,
    "atk": 4,
    "life": 3,
    "evo_atk": 6,
    "evo_life": 5,
    "rarity": 4,
    "get_red_ether": 1000,
    "use_red_ether": 3500,
    "description": "远古缔结的约定，沉眠于古老的黑暗中。<br>即便人类逝去，物换星移，魔神仍不会遗忘。<br>想起吧。那染上低俗光芒的漆黑之暗。",
    "evo_description": "真正的契约不会以纸张，也不会以鲜血，<br>而是用灵魂来缔结。<br>在疼痛及苦楚前，交换彼此的罪孽吧。<br>他会给予同等价值的恩惠。魔神，比神明还要老实。",
    "cv": "竹内良太",
    "copyright": null,
    "base_card_id": 117641020,
    "normal_card_id": 117641020,
    "format_type": 0,
    "restricted_count": 3,
    "restricted_count_co_main": 3,
    "restricted_count_co_sub": 3
}