{
    "card_id": 121411010,
    "foil_card_id": 121411011,
    "card_set_id": 10021,
    "card_name": "激进派的侦察兵",
    "card_name_ruby": "",
    "is_foil": 0,
    "char_type": 1,
    "clan": 4,
    "tribe_name": "自然",
    "skill": "token_draw//damage",
    "skill_condition": "character=me//character=me",
    "skill_target": "none//character=op&target=inplay&card_type=unit_and_class&select_count=1",
    "skill_option": "token_draw=900012010:900012010//damage=2",
    "skill_preprocess": "none//none",
    "skill_disc": "入场曲 增加2张那塔拉的大树卡片到手牌中。",
    "org_skill_disc": "[u][ffcd45]入场曲[-][/u] 增加2张[u][ffcd45]那塔拉的大树[-][/u]卡片到手牌中。",
    "evo_skill_disc": "进化时 给予敌方的主战者或1个敌方的从者2点伤害。",
    "org_evo_skill_disc": "[u][ffcd45]进化时[-][/u] 给予敌方的主战者或1个敌方的从者2点伤害。",
    "cost": 3,
    "atk": 3,
    "life": 2,
    "evo_atk": 5,
    "evo_life": 4,
    "rarity": 1,
    "get_red_ether": 10,
    "use_red_ether": 50,
    "description": "听好了，钢铁人还不习惯森林的野兽！<br>如果看到凶猛的家伙，要优先捕捉喔！<br>我们要多抓一点猎物，吓吓稳健派那些人！",
    "evo_description": "充满干劲结果还从树上掉下来……真是有够丢脸的。<br>如果没有钢铁人接住我的话早就受伤了，谢啦。<br>但这件事，可以帮我跟队长保密吗？",
    "cv": "町山芹菜",
    "copyright": null,
    "base_card_id": 121411010,
    "normal_card_id": 121411010,
    "format_type": 0,
    "restricted_count": 3,
    "restricted_count_co_main": 3,
    "restricted_count_co_sub": 3
}