{
    "card_id": 110031010,
    "foil_card_id": 110031011,
    "card_set_id": 10010,
    "card_name": "爆烈佣兵‧菲娜",
    "card_name_ruby": "",
    "is_foil": 0,
    "char_type": 1,
    "clan": 0,
    "tribe_name": "-",
    "skill": "damage//destroy",
    "skill_condition": "character=op&target=inplay&card_type=unit_and_class//character=me&target=self&card_type=unit",
    "skill_target": "character=op&target=inplay&card_type=unit_and_class&select_count=1//character=op&target=inplay&card_type=unit&status_cost<=1",
    "skill_option": "damage=1//none",
    "skill_preprocess": "none//none",
    "skill_disc": "入场曲 给予敌方的主战者或1个敌方的从者1点伤害。",
    "org_skill_disc": "[u][ffcd45]入场曲[-][/u] 给予敌方的主战者或1个敌方的从者1点伤害。",
    "evo_skill_disc": "进化时 破坏全部消费为1以下的敌方从者。",
    "org_evo_skill_disc": "[u][ffcd45]进化时[-][/u] 破坏全部消费为1以下的敌方从者。",
    "cost": 4,
    "atk": 3,
    "life": 3,
    "evo_atk": 5,
    "evo_life": 5,
    "rarity": 3,
    "get_red_ether": 250,
    "use_red_ether": 800,
    "description": "「走吧，迷你哥布！我们去寻宝吧！」<br>「啊！菲姐姐，人家找到闪亮亮了哥布！」<br>「迷、迷你哥布！那是陷阱的开关――」<br>――误触陷阱的菲娜和迷你哥布",
    "evo_description": "「在、在本大小姐菲娜的字典里没有失败两个字！」<br>「啊！发现闪亮亮的地板了哥布！嘿咻！」<br>「……迷你哥布，刚才是不是有「卡锵」的声音？」<br>――掉进地洞里的菲娜和迷你哥布",
    "cv": "户松遥",
    "copyright": null,
    "base_card_id": 110031010,
    "normal_card_id": 110031010,
    "format_type": 0,
    "restricted_count": 3,
    "restricted_count_co_main": 3,
    "restricted_count_co_sub": 3
}