{
    "card_id": 715221010,
    "foil_card_id": 715221011,
    "card_set_id": 70021,
    "card_name": "生还的突击兵",
    "card_name_ruby": "",
    "is_foil": 0,
    "char_type": 1,
    "clan": 2,
    "tribe_name": "士兵",
    "skill": "rush,update_deck,powerup",
    "skill_condition": "character=me,character=me,character=me",
    "skill_target": "character=me&target=self&card_type=unit,none,character=me&target=deck&card_type=all&base_card_id=120221020",
    "skill_option": "none,token_draw=715221010&type=add,add_offense=1&add_life=1",
    "skill_preprocess": "none,none,none",
    "skill_disc": "突进 <br>谢幕曲 增加1张生还的突击兵卡片到牌堆中。给予全部自己牌堆中的生还的突击兵+1/+1效果。",
    "org_skill_disc": "[u][ffcd45]突进[-][/u] <br>[u][ffcd45]谢幕曲[-][/u] 增加1张[u][ffcd45]生还的突击兵[-][/u]卡片到牌堆中。给予全部自己牌堆中的[u][ffcd45]生还的突击兵[-][/u]+1/+1效果。",
    "evo_skill_disc": "与进化前能力相同。",
    "org_evo_skill_disc": "与进化前能力相同。",
    "cost": 1,
    "atk": 1,
    "life": 1,
    "evo_atk": 3,
    "evo_life": 3,
    "rarity": 2,
    "get_red_ether": 0,
    "use_red_ether": 0,
    "description": "惹人怜爱的突击兵，<br>她手中的枪总是成为开战的烽火。<br>后排的士兵们迢迢追赶，朝著敌阵倾巢而出。<br>「接著就是……展开愉悦的战争啦～！」",
    "evo_description": "该突击兵非常善于晋升及生还之术。<br>只要以开路先锋的身影取得荣耀，<br>即可在不为人知的情况下乘乱脱逃。<br>「直到平安回家前都是战争喔！」",
    "cv": "上坂すみれ",
    "copyright": null,
    "base_card_id": 120221020,
    "normal_card_id": 715221010,
    "format_type": 0,
    "restricted_count": 3,
    "restricted_count_co_main": 3,
    "restricted_count_co_sub": 3
}