{
    "card_id": 121011010,
    "foil_card_id": 121011011,
    "card_set_id": 10021,
    "card_name": "福音天使",
    "card_name_ruby": "",
    "is_foil": 0,
    "char_type": 1,
    "clan": 0,
    "tribe_name": "-",
    "skill": "random_array,powerup,guard,heal,draw,pp_fixeduse,powerup,guard,heal,draw",
    "skill_condition": "pp_count<6,pp_count<6,pp_count<6,pp_count<6,pp_count<6,pp_count>=6,pp_count>=6,pp_count>=6,pp_count>=6,pp_count>=6",
    "skill_target": "character=me&target=self&card_type=unit,character=me&target=self,character=me&target=self,character=me&target=inplay&card_type=class,character=me&target=deck&card_type=all&random_count=1,none,character=me&target=self,character=me&target=self,character=me&target=inplay&card_type=class,character=me&target=deck&card_type=all&random_count=1",
    "skill_option": "sum=1&random_range=3,add_offense=1&add_life=1,none,healing=4,none,fixeduse=6,add_offense=1&add_life=1,none,healing=4,none",
    "skill_preprocess": "none,only_random_index=0,only_random_index=0,only_random_index=1,only_random_index=2,none,none,none,none,none",
    "skill_disc": "入场曲 由「获得+1/+1与守护 效果」、「回复自己的主战者4点生命值」、「抽取1张卡片」之中，随机发动1种能力。<br>爆能强化 6； 由原本的随机发动1种转变为每种能力各发动1次。",
    "org_skill_disc": "[u][ffcd45]入场曲[-][/u] 由「获得+1/+1与[u][ffcd45]守护[-][/u] 效果」、「回复自己的主战者4点生命值」、「抽取1张卡片」之中，随机发动1种能力。<br>[u][ffcd45]爆能强化[-][/u] 6； 由原本的随机发动1种转变为每种能力各发动1次。",
    "evo_skill_disc": "",
    "org_evo_skill_disc": "",
    "cost": 4,
    "atk": 3,
    "life": 4,
    "evo_atk": 5,
    "evo_life": 6,
    "rarity": 1,
    "get_red_ether": 10,
    "use_red_ether": 50,
    "description": "神叫我过去……但是，为什么是到地上？<br>该怎么办呢～降临后就赐予你我的庇护吧～",
    "evo_description": "听说似乎有大规模的战斗，而这件是战斗服装。<br>咦？但是，你会在这里不就代表……？",
    "cv": "鸟越まあや",
    "copyright": null,
    "base_card_id": 121011010,
    "normal_card_id": 121011010,
    "format_type": 0,
    "restricted_count": 3,
    "restricted_count_co_main": 3,
    "restricted_count_co_sub": 3
}