{
    "card_id": 118724010,
    "foil_card_id": 118724011,
    "card_set_id": 10018,
    "card_name": "纯净的转变",
    "card_name_ruby": "",
    "is_foil": 0,
    "char_type": 4,
    "clan": 7,
    "tribe_name": "-",
    "skill": "metamorphose",
    "skill_condition": "character=me",
    "skill_target": "character=both&target=inplay&card_type=unit_and_allfield&select_count=1",
    "skill_option": "metamorphose=900713010",
    "skill_preprocess": "none",
    "skill_disc": "使1张战场上的卡片变身为神圣的开示。",
    "org_skill_disc": "使1张战场上的卡片变身为[u][ffcd45]神圣的开示[-][/u]。",
    "evo_skill_disc": "",
    "org_evo_skill_disc": "",
    "cost": 2,
    "atk": 0,
    "life": 0,
    "evo_atk": 0,
    "evo_life": 0,
    "rarity": 2,
    "get_red_ether": 50,
    "use_red_ether": 200,
    "description": "若能化为有形将不再痛苦。神会予以精妙的恩宠。",
    "evo_description": "",
    "cv": "-",
    "copyright": null,
    "base_card_id": 118724010,
    "normal_card_id": 118724010,
    "format_type": 0,
    "restricted_count": 3,
    "restricted_count_co_main": 3,
    "restricted_count_co_sub": 3
}