{
    "card_id": 717731020,
    "foil_card_id": 717731021,
    "card_set_id": 10026,
    "card_name": "绚彩瑰石‧玟奇",
    "card_name_ruby": "",
    "is_foil": 0,
    "char_type": 1,
    "clan": 7,
    "tribe_name": "-",
    "skill": "guard,quick",
    "skill_condition": "character=me,{me.game_crystallized_cards.count}>=5",
    "skill_target": "character=me&target=inplay&card_type=unit&status_offense<=2,character=me&target=inplay&card_type=unit&status_offense<=2",
    "skill_option": "none,none",
    "skill_preprocess": "none,none",
    "skill_disc": "入场曲 给予全部自己「攻击力为2以下的从者」守护 效果。如果自己在这场对战中已发动结晶 的卡片为5张以上，则会额外再给予疾驰 效果。",
    "org_skill_disc": "[u][ffcd45]入场曲[-][/u] 给予全部自己「攻击力为2以下的从者」[u][ffcd45]守护[-][/u] 效果。如果自己在这场对战中已发动[u][ffcd45]结晶[-][/u] 的卡片为5张以上，则会额外再给予[u][ffcd45]疾驰[-][/u] 效果。",
    "evo_skill_disc": "",
    "org_evo_skill_disc": "",
    "cost": 1,
    "atk": 1,
    "life": 1,
    "evo_atk": 3,
    "evo_life": 3,
    "rarity": 3,
    "get_red_ether": 250,
    "use_red_ether": 0,
    "description": "「真没劲。又不是小孩了，为什么要做这种事……」<br>「玟奇、玟、玟──奇！」<br>「……总之，如果好玩的话就算了。」<br>──小鸟游 翼与玟奇",
    "evo_description": "「拿太多了啦。而且吃这么多会胖的。」<br>「玟、奇──！」<br>「就说我知道了嘛。……去分给那些家伙吃吧。」<br>──小鸟游 翼与玟奇",
    "cv": "富田美忧",
    "copyright": null,
    "base_card_id": 126731010,
    "normal_card_id": 717731020,
    "format_type": 1,
    "restricted_count": 3,
    "restricted_count_co_main": 3,
    "restricted_count_co_sub": 3
}