{
    "card_id": 900634030,
    "foil_card_id": 900634031,
    "card_set_id": 90000,
    "card_name": "莫诺的觉悟",
    "card_name_ruby": "",
    "is_foil": 0,
    "char_type": 4,
    "clan": 6,
    "tribe_name": "-",
    "skill": "possess_ep_modifier",
    "skill_condition": "character=me",
    "skill_target": "character=me&target=inplay&card_type=class",
    "skill_option": "add_ep=1",
    "skill_preprocess": "none",
    "skill_disc": "回复自己的EP 1点。",
    "org_skill_disc": "回复自己的EP 1点。",
    "evo_skill_disc": "",
    "org_evo_skill_disc": "",
    "cost": 0,
    "atk": 0,
    "life": 0,
    "evo_atk": 0,
    "evo_life": 0,
    "rarity": 3,
    "get_red_ether": 0,
    "use_red_ether": 0,
    "description": "我是否也加入战斗行列呢。<br>唉呀唉呀，真是伤脑筋……<br>我是柔弱的淑女、折损的螺丝。勉强可是倍感痛苦。<br>算了，反正也已苟活至今，那就决定享受余生了。",
    "evo_description": "",
    "cv": "佐仓绫音",
    "copyright": null,
    "base_card_id": 900634030,
    "normal_card_id": 900634030,
    "format_type": 0,
    "restricted_count": 3,
    "restricted_count_co_main": 3,
    "restricted_count_co_sub": 3
}