{
    "card_id": 101311060,
    "foil_card_id": 101311061,
    "card_set_id": 10001,
    "card_name": "见习炼金术师",
    "card_name_ruby": "",
    "is_foil": 0,
    "char_type": 1,
    "clan": 3,
    "tribe_name": "-",
    "skill": "token_draw",
    "skill_condition": "character=me",
    "skill_target": "none",
    "skill_option": "token_draw=900314010",
    "skill_preprocess": "destroy_tribe=white_ritual",
    "skill_disc": "入场曲 土之秘术 增加1张守护者炼成术卡片到手牌中。",
    "org_skill_disc": "[u][ffcd45]入场曲[-][/u] [u][ffcd45]土之秘术[-][/u] 增加1张[u][ffcd45]守护者炼成术[-][/u]卡片到手牌中。",
    "evo_skill_disc": "",
    "org_evo_skill_disc": "",
    "cost": 2,
    "atk": 2,
    "life": 2,
    "evo_atk": 4,
    "evo_life": 4,
    "rarity": 1,
    "get_red_ether": 10,
    "use_red_ether": 50,
    "description": "唔……材料没有弄错。顺序也跟书上写的一样，这样应该就做得出灵药了才对啊……嗯嗯……是不是该再加点龙之石试试看啊。",
    "evo_description": "喔喔？这个该不会……嗯！这是新的灵药吧……文献里也没有记载过。真没想到会做出这种私房秘药，果然失败为成功之母这句话不是骗人的呢！",
    "cv": "门脇舞以",
    "copyright": null,
    "base_card_id": 101311060,
    "normal_card_id": 101311060,
    "format_type": 0,
    "restricted_count": 3,
    "restricted_count_co_main": 3,
    "restricted_count_co_sub": 3
}