{
    "card_id": 109631010,
    "foil_card_id": 109631011,
    "card_set_id": 10009,
    "card_name": "邪眼恶魔",
    "card_name_ruby": "",
    "is_foil": 0,
    "char_type": 1,
    "clan": 6,
    "tribe_name": "-",
    "skill": "pp_fixeduse,transform//damage",
    "skill_condition": "{me.inplay.class.pp}>=2&{me.inplay.class.pp}<{me.hand_self.cost}&{op.inplay.unit.selectable.count}>0,{me.inplay.class.pp}>=2&{me.inplay.class.pp}<{me.hand_self.cost}&{op.inplay.unit.selectable.count}>0//character=op&target=inplay&card_type=unit",
    "skill_target": "none,none//character=op&target=inplay&card_type=unit",
    "skill_option": "fixeduse=2,card_id=800634010//damage={me.inplay.class.damage_count=self}",
    "skill_preprocess": "none,none//none",
    "skill_disc": "激奏 2； 给予自己的主战者1点伤害，并给予1个敌方的从者3点伤害。",
    "org_skill_disc": "[u][ffcd45]激奏[-][/u] 2； 给予自己的主战者1点伤害，并给予1个敌方的从者3点伤害。",
    "evo_skill_disc": "进化时 给予敌方的从者全体与「这场对战中，自己的主战者于自己的回合中受到伤害的次数」等量的伤害。",
    "org_evo_skill_disc": "[u][ffcd45]进化时[-][/u] 给予敌方的从者全体与「这场对战中，自己的主战者于自己的回合中受到伤害的次数」等量的伤害。",
    "cost": 5,
    "atk": 5,
    "life": 4,
    "evo_atk": 5,
    "evo_life": 4,
    "rarity": 3,
    "get_red_ether": 250,
    "use_red_ether": 800,
    "description": "憎恨只会引火上身。<br>烧焦的躯体歪斜而扭曲。<br>──啊，如果没有你们在，我也不会有如此痛楚。<br>──啊，我会恨你们，直到万物枯竭。",
    "evo_description": "你们称我为恶魔，但究竟怎样才算「恶」呢？<br>我只不过是生来就带有必然的憎恶罢了。<br>比起来，应该是你们这群伤害我的家伙──<br>才该尝尝何谓真正的「恶」！",
    "cv": "藤村步",
    "copyright": null,
    "base_card_id": 109631010,
    "normal_card_id": 109631010,
    "format_type": 0,
    "restricted_count": 3,
    "restricted_count_co_main": 3,
    "restricted_count_co_sub": 3
}