{
    "card_id": 116131020,
    "foil_card_id": 116131021,
    "card_set_id": 10016,
    "card_name": "铁扇精灵",
    "card_name_ruby": "",
    "is_foil": 0,
    "char_type": 1,
    "clan": 1,
    "tribe_name": "机械",
    "skill": "draw,cost_change//draw,cost_change",
    "skill_condition": "character=me,character=me//character=me,character=me",
    "skill_target": "character=me&target=deck&card_type=all&tribe=machine&base_card_id!=116131020&random_count=1,character=me&target=skill_drew_card&card_type=all//character=me&target=deck&card_type=all&tribe=machine&base_card_id!=116131020&random_count=1,character=me&target=skill_drew_card&card_type=all",
    "skill_option": "none,add=-1//none,add=-1",
    "skill_preprocess": "none,none//none,none",
    "skill_disc": "入场曲 随机将1张机械卡（铁扇精灵除外），由自己的牌堆抽取到手牌中，并使其消费-1。",
    "org_skill_disc": "[u][ffcd45]入场曲[-][/u] 随机将1张机械卡（[u][ffcd45]铁扇精灵[-][/u]除外），由自己的牌堆抽取到手牌中，并使其消费-1。",
    "evo_skill_disc": "进化时 随机将1张机械卡（铁扇精灵除外），由自己的牌堆抽取到手牌中，并使其消费-1。",
    "org_evo_skill_disc": "[u][ffcd45]进化时[-][/u] 随机将1张机械卡（[u][ffcd45]铁扇精灵[-][/u]除外），由自己的牌堆抽取到手牌中，并使其消费-1。",
    "cost": 4,
    "atk": 5,
    "life": 3,
    "evo_atk": 7,
    "evo_life": 5,
    "rarity": 3,
    "get_red_ether": 250,
    "use_red_ether": 800,
    "description": "精灵的武器改变了型态，完成更进一步的激进化。<br>刮起的风能让身体乘其而行，入侵者也被全数吹飞。<br>连风也能操控的机械。那就是超越大地之力的证明。<br>──精灵的森林笔记‧3",
    "evo_description": "挥舞著机械，生活在森林里的众人增强了力量。<br>对于依然拒绝改变的大地──他们下定了决心。<br>必须以机械，将拒绝改变的古老大地全面翻新。<br>──繁荣之绿‧3",
    "cv": "天崎滉平",
    "copyright": null,
    "base_card_id": 116131020,
    "normal_card_id": 116131020,
    "format_type": 0,
    "restricted_count": 3,
    "restricted_count_co_main": 3,
    "restricted_count_co_sub": 3
}