{
    "card_id": 120621020,
    "foil_card_id": 120621021,
    "card_set_id": 10020,
    "card_name": "霹雷恶魔",
    "card_name_ruby": "",
    "is_foil": 0,
    "char_type": 1,
    "clan": 6,
    "tribe_name": "-",
    "skill": "damage,heal,draw//attach_skill",
    "skill_condition": "{op.inplay.unit.selectable.count}>0,character=me,character=me//character=me",
    "skill_target": "character=op&target=inplay&card_type=unit&select_count=1,character=me&target=inplay&card_type=class,character=me&target=deck&card_type=all&random_count=1//character=me&target=inplay&card_type=class",
    "skill_option": "damage=3,healing=3,none//skill=(skill:draw)(timing:self_turn_start)(condition:character=me)(target:character=me&target=deck&card_type=unit&clan=vampire&random_count=1)(option:none)(preprocess:remove_after_action=(count=1))",
    "skill_preprocess": "none,none,none//none",
    "skill_disc": "入场曲 给予1个敌方的从者3点伤害。回复自己的主战者3点生命值。抽取1张卡片。",
    "org_skill_disc": "[u][ffcd45]入场曲[-][/u] 给予1个敌方的从者3点伤害。回复自己的主战者3点生命值。抽取1张卡片。",
    "evo_skill_disc": "进化时 下个自己的回合开始时，随机将1张吸血鬼从者卡，由自己的牌堆抽取到手牌中。",
    "org_evo_skill_disc": "[u][ffcd45]进化时[-][/u] 下个自己的回合开始时，随机将1张吸血鬼从者卡，由自己的牌堆抽取到手牌中。",
    "cost": 5,
    "atk": 3,
    "life": 5,
    "evo_atk": 5,
    "evo_life": 7,
    "rarity": 2,
    "get_red_ether": 50,
    "use_red_ether": 200,
    "description": "「从天而降的那道光芒，在我的家乡被称为神鸣。<br>看见那家伙的样子后，我才发现那称呼是错误的。」<br>──某位战士的日记",
    "evo_description": "「恶魔只要将手朝天空高举，<br>光芒便会如服从般地降下。我领悟到了──<br>那从天而降的光芒，是神的悲鸣。」<br>──某位战士的日记",
    "cv": "桧山修之",
    "copyright": null,
    "base_card_id": 120621020,
    "normal_card_id": 120621020,
    "format_type": 0,
    "restricted_count": 3,
    "restricted_count_co_main": 3,
    "restricted_count_co_sub": 3
}